aicodec/cli.py
aicodec/review_server.py
aicodec/utils.py
aicodec/core/__init__.py
aicodec/core/config.py
aicodec/core/models.py
aicodec/services/__init__.py
aicodec/services/encoder_service.py
aicodec_test-1.0.0.dist-info/licenses/LICENSE
tests/__init__.py
tests/test_cli.py
tests/test_encoder_service.py
tests/test_review_server.py
aicodec_test-1.0.0.dist-info/METADATA
aicodec_test-1.0.0.dist-info/WHEEL
aicodec_test-1.0.0.dist-info/entry_points.txt
aicodec_test-1.0.0.dist-info/top_level.txt
aicodec_test-1.0.0.dist-info/RECORD
