Metadata-Version: 2.4
Name: aicodec_test
Version: 1.0.0
Summary: A lightweight communication layer for developers to interact with LLMs.
Author-email: Your Name <your.email@example.com>
License: MIT License
Classifier: License :: OSI Approved :: MIT License
Classifier: Programming Language :: Python :: 3
License-File: LICENSE
Requires-Dist: jsonschema
Requires-Dist: pyperclip
Requires-Dist: pathspec
Provides-Extra: dev
Requires-Dist: pytest; extra == "dev"
Requires-Dist: pytest-mock; extra == "dev"
Requires-Dist: pytest-cov; extra == "dev"
Requires-Dist: pytest-html; extra == "dev"
Requires-Dist: requests; extra == "dev"
Dynamic: license-file
